Workbook

Sheet Sheet2
A1: Order ID | B1: Order Date | C1: Customer Name | D1: City | E1: Product | F1: Category | G1: Quantity | H1: Unit Price | I1: Sales | J1: Payment Mode | K1: Salesperson
A2: 1049 | B2: 46146 | C2: Manav | D2: Pune | E2: Headphones | F2: Accessories | G2: 5 | H2: 2100 | I2: 10500 | J2: Cash | K2: Rahul
A3: 1042 | B3: 23/03/2026 | C3: Ayesha | D3: Pune | E3: Headphones | F3: Accessories | G3: 3 | H3: 2250 | I3: 6750 | J3: UPI | K3: Neha
A4: 1036 | B4: 46329 | C4: Hiba | D4: Pune | E4: Headphones | F4: Accessories | G4: 4 | H4: 2150 | I4: 8600 | J4: UPI | K4: Priya
A5: 1030 | B5: 27/02/2026 | C5: Samaira | D5: Pune | E5: Headphones | F5: Accessories | G5: 6 | H5: 2000 | I5: 12000 | J5: Cash | K5: Neha
A6: 1005 | B6: 46204 | C6: Aditya | D6: Mumbai | E6: Headphones | F6: Accessories | G6: 4 | H6: 2000 | I6: 8000 | J6: Card | K6: Rahul
A7: 1024 | B7: 15/02/2026 | C7: Shruti | D7: Nashik | E7: Headphones | F7: Accessories | G7: 2 | H7: 2300 | I7: 4600 | J7: Cash | K7: Priya
A8: 1018 | B8: 46083 | C8: Diya | D8: Pune | E8: Headphones | F8: Accessories | G8: 5 | H8: 2100 | I8: 10500 | J8: Cash | K8: Neha
A9: 1011 | B9: 19/01/2026 | C9: Vihaan | D9: Pune | E9: Headphones | F9: Accessories | G9: 3 | H9: 2200 | I9: 6600 | J9: Cash | K9: Amit

Sheet Sheet1
A3: Row Labels | B3: Sum of Sales
A4: Headphones | B4: 67550
A5: Keyboard | B5: 47500
A6: Laptop | B6: 596000
A7: Monitor | B7: 141200
A8: Mouse | B8: 35810
A9: Printer | B9: 165000
A10: Grand Total | B10: 1053060

Sheet Sheet4
A3: Row Labels | B3: Sum of Sales
A4: Mumbai | B4: 309940
A5: Nagpur | B5: 145000
A6: Nashik | B6: 161900
A7: Pune | B7: 436220
A8: Grand Total | B8: 1053060

Sheet Sheet5
A3: Row Labels | B3: Sum of Sales
A4: Accessories | B4: 150860
A5: Electronics | B5: 902200
A6: Grand Total | B6: 1053060

Sheet Sheet6
A3: Row Labels | B3: Sum of Sales
A4: Amit | B4: 338100
A5: Neha | B5: 180290
A6: Priya | B6: 192650
A7: Rahul | B7: 342020
A8: Grand Total | B8: 1053060

Sheet Sheet7
A3: Row Labels | B3: Sum of Sales
A4: 1 | B4: 305300
A5: 2 | B5: 295300
A6: 3 | B6: 341960
A7: 4 | B7: 110500
A8: Grand Total | B8: 1053060

Sheet Raw data
A1: Order ID | B1: Order Date | C1: Customer Name | D1: City | E1: Product | F1: Category | G1: Quantity | H1: Unit Price | I1: Sales | J1: Payment Mode | K1: Salesperson | L1: Month
A2: 1001 | B2: 46023 | C2: Aarav | D2: Pune | E2: Laptop | F2: Electronics | G2: 1 | H2: 55000 | I2: 55000 | J2: UPI | K2: Rahul | L2: =MONTH(Salesdata[[#This Row],[Order Date]]) -> 1
A3: 1002 | B3: 46024 | C3: Priya | D3: Mumbai | E3: Mouse | F3: Accessories | G3: 3 | H3: 800 | I3: 2400 | J3: Cash | K3: Neha | L3: =MONTH(Salesdata[[#This Row],[Order Date]]) -> 1
A4: 1003 | B4: 46025 | C4: Rohan | D4: Nashik | E4: Keyboard | F4: Accessories | G4: 2 | H4: 1500 | I4: 3000 | J4: Card | K4: Amit | L4: =MONTH(Salesdata[[#This Row],[Order Date]]) -> 1
A5: 1004 | B5: 46027 | C5: Sana | D5: Pune | E5: Monitor | F5: Electronics | G5: 1 | H5: 12000 | I5: 12000 | J5: UPI | K5: Priya | L5: =MONTH(Salesdata[[#This Row],[Order Date]]) -> 1
A6: 1005 | B6: 46029 | C6: Aditya | D6: Mumbai | E6: Headphones | F6: Accessories | G6: 4 | H6: 2000 | I6: 8000 | J6: Card | K6: Rahul | L6: =MONTH(Salesdata[[#This Row],[Order Date]]) -> 1
A7: 1006 | B7: 46031 | C7: Fatima | D7: Pune | E7: Laptop | F7: Electronics | G7: 1 | H7: 62000 | I7: 62000 | J7: UPI | K7: Neha | L7: =MONTH(Salesdata[[#This Row],[Order Date]]) -> 1
A8: 1007 | B8: 46033 | C8: Arjun | D8: Nagpur | E8: Keyboard | F8: Accessories | G8: 5 | H8: 1400 | I8: 7000 | J8: Cash | K8: Amit | L8: =MONTH(Salesdata[[#This Row],[Order Date]]) -> 1
A9: 1008 | B9: 46035 | C9: Anaya | D9: Pune | E9: Printer | F9: Electronics | G9: 1 | H9: 15000 | I9: 15000 | J9: Card | K9: Priya | L9: =MONTH(Salesdata[[#This Row],[Order Date]]) -> 1
A10: 1009 | B10: 46037 | C10: Kabir | D10: Mumbai | E10: Mouse | F10: Accessories | G10: 6 | H10: 750 | I10: 4500 | J10: UPI | K10: Rahul | L10: =MONTH(Salesdata[[#This Row],[Order Date]]) -> 1
A11: 1010 | B11: 46039 | C11: Ishita | D11: Nashik | E11: Monitor | F11: Electronics | G11: 2 | H11: 11000 | I11: 22000 | J11: Card | K11: Neha | L11: =MONTH(Salesdata[[#This Row],[Order Date]]) -> 1
A12: 1011 | B12: 46041 | C12: Vihaan | D12: Pune | E12: Headphones | F12: Accessories | G12: 3 | H12: 2200 | I12: 6600 | J12: Cash | K12: Amit | L12: =MONTH(Salesdata[[#This Row],[Order Date]]) -> 1
A13: 1012 | B13: 46043 | C13: Zoya | D13: Mumbai | E13: Laptop | F13: Electronics | G13: 1 | H13: 58000 | I13: 58000 | J13: UPI | K13: Priya | L13: =MONTH(Salesdata[[#This Row],[Order Date]]) -> 1
... A51: 1050 | B51: 46119 | C51: Anvi | D51: Nagpur | E51: Printer | F51: Electronics | G51: 1 | H51: 15000 | I51: 15000 | J51: UPI | K51: Neha | L51: =MONTH(Salesdata[[#This Row],[Order Date]]) -> 4

Sheet Analysis
A1: Sales analysis
A3: Total | B3: =SUM('Raw data'!I:I) -> 1053060 | D3: Electronics | E3: =SUMIF(Salesdata[Category],Analysis!D3,Salesdata[Sales]) -> 902200 | G3: City | H3: Total Sales | J3: Salesperson | K3: Total Sales
D4: accessories | E4: =SUMIF(Salesdata[Category],Analysis!D4,Salesdata[Sales]) -> 150860 | G4: Pune | H4: =SUMIF('Raw data'!D28:D51,Analysis!G4,Salesdata[Unit Price]) -> 255450 | J4: Rahul | K4: =SUMIF(Salesdata[Salesperson],Analysis!J4,Salesdata[Sales]) -> 342020
A5: Total quantity sold | B5: =SUM('Raw data'!G:G) -> 141 | D5: Total | E5: =SUM(E3:E4) -> 1053060 | G5: Mumbai | H5: =SUMIF('Raw data'!D29:D52,Analysis!G5,Salesdata[Unit Price]) -> 92350 | J5: Neha | K5: =SUMIF(Salesdata[Salesperson],Analysis!J5,Salesdata[Sales]) -> 180290
G6: Nashik | H6: =SUMIF('Raw data'!D30:D53,Analysis!G6,Salesdata[Unit Price]) -> 62100 | J6: Amit | K6: =SUMIF(Salesdata[Salesperson],Analysis!J6,Salesdata[Sales]) -> 338100
G7: Nagpur | H7: =SUMIF('Raw data'!D31:D54,Analysis!G7,Salesdata[Unit Price]) -> 17350 | J7: Priya | K7: =SUMIF(Salesdata[Salesperson],Analysis!J7,Salesdata[Sales]) -> 192650
A8: Total orders | B8: =COUNTA(Salesdata[Order ID]) -> 50
D9: Payment Mode | E9: Total Sales
A10: Average order value | B10: =B3/B8 -> 21061.2 | D10: UPI | E10: =SUMIF(Salesdata[Payment Mode],Analysis!D10,Salesdata[Sales]) -> 631600
D11: Cash | E11: =SUMIF(Salesdata[Payment Mode],Analysis!D11,Salesdata[Sales]) -> 96460
A12: Product | B12: Total sale | D12: Card | E12: =SUMIF(Salesdata[Payment Mode],Analysis!D12,Salesdata[Sales]) -> 325000
A13: Laptop | B13: =SUMIF(Salesdata[Product],Analysis!A13,Salesdata[Sales]) -> 596000
A14: Mouse | B14: =SUMIF(Salesdata[Product],Analysis!A14,Salesdata[Sales]) -> 35810 | D14: Month | E14: Total Sales
A15: Keyboard | B15: =SUMIF(Salesdata[Product],Analysis!A15,Salesdata[Sales]) -> 47500 | D15: January | E15: =SUMIF(Salesdata[Month],1,Salesdata[Sales]) -> 305300
A16: Monitor | B16: =SUMIF(Salesdata[Product],Analysis!A16,Salesdata[Sales]) -> 141200 | D16: February | E16: =SUMIF(Salesdata[Month],2,Salesdata[Sales]) -> 295300
A17: Headphones | B17: =SUMIF(Salesdata[Product],Analysis!A17,Salesdata[Sales]) -> 67550 | D17: March | E17: =SUMIF(Salesdata[Month],3,Salesdata[Sales]) -> 341960
A18: Printer | B18: =SUMIF(Salesdata[Product],Analysis!A18,Salesdata[Sales]) -> 165000 | D18: April | E18: =SUMIF(Salesdata[Month],4,Salesdata[Sales]) -> 110500

Sheet dashboard
A1: SALES ANALYTICS DASHBOARD
A3: TOTAL SALES | B3: TOTAL QUANTITY | C3: TOTAL ORDERS | D3: AVERAGE ORDER VALUE
A4: =Analysis!B3 -> 1053060 | B4: =Analysis!B5 -> 141 | C4: =Analysis!B8 -> 50 | D4: =Analysis!B10 -> 21061.2
A28: Business Insights
A34: Laptop generated the highest sales among all products. | B34: Electronics contributed the majority of total sales. | C34: Pune was the highest-performing city by sales. | D34: Rahul generated the highest sales among the salespeople. | E34: March recorded the highest monthly sales

Sheet Sheet9

Sheet Sheet10
